LICENSE
MANIFEST.in
README.md
setup.cfg
setup.py
tahoe/__init__.py
tahoe/aws.py
tahoe/encoding.py
tahoe/exceptions.py
tahoe/fixtures.py
tahoe/forms.py
tahoe/misc.py
tahoe/queries.py
tahoe/search.py
tahoe/sessions.py
tahoe/tasks.py
tahoe/tests.py
tahoe/views.py
tahoe.egg-info/PKG-INFO
tahoe.egg-info/SOURCES.txt
tahoe.egg-info/dependency_links.txt
tahoe.egg-info/not-zip-safe
tahoe.egg-info/requires.txt
tahoe.egg-info/top_level.txt
tahoe/models/__init__.py
tahoe/models/mixins/__init__.py
tahoe/models/mixins/encodable.py
tahoe/models/mixins/searchable.py
tahoe/models/mixins/timestampable.py
tests/__init__.py
tests/test_encoding.py
tests/test_misc.py
tests/test_model_mixins.py
tests/test_models.py
tests/app/__init__.py
tests/app/config.py
tests/app/models/__init__.py
tests/app/models/account.py
tests/app/models/role.py
tests/app/tasks/__init__.py
tests/app/views/__init__.py