Metadata-Version: 1.1
Name: tahoe
Version: 1.0.3.1
Summary: A Flask-based framework that handles the tedious things
Home-page: http://lunarcorp.github.io/tahoe/
Author: Clint Ecker
Author-email: clint@ltc.io
License: The MIT License: http://www.opensource.org/licenses/mit-license.php
Download-URL: https://github.com/lunarcorp/tahoe
Platform: any
Classifier: Development Status :: 5 - Production/Stable
Classifier: Intended Audience :: Developers
Classifier: Operating System :: OS Independent
Classifier: License :: OSI Approved :: MIT License
Classifier: Programming Language :: Python :: 2.7
Classifier: Topic :: Software Development :: Libraries :: Python Modules
